medium_converter/__init__.py
medium_converter/cli.py
medium_converter/core/__init__.py
medium_converter/core/auth.py
medium_converter/core/fetcher.py
medium_converter/core/models.py
medium_converter/core/parser.py
medium_converter/exporters/__init__.py
medium_converter/exporters/base.py
medium_converter/exporters/markdown.py
medium_converter/exporters/pdf.py
medium_converter/llm/__init__.py
medium_converter/llm/config.py
medium_converter/llm/enhancer.py
medium_converter/llm/prompts.py
medium_converter/llm/providers.py
medium_converter/utils/__init__.py
medium_converter/utils/helpers.py
medium_converter-0.1.0.dist-info/LICENSE
medium_converter-0.1.0.dist-info/METADATA
medium_converter-0.1.0.dist-info/WHEEL
medium_converter-0.1.0.dist-info/entry_points.txt
medium_converter-0.1.0.dist-info/RECORD
