Metadata-Version: 2.3
Name: medium-converter
Version: 0.1.0
Summary: Convert Medium articles to various formats with LLM enhancement
License: MIT
Author: Marcus Elwin
Author-email: marcus@elwin.com
Requires-Python: >=3.11,<4.0
Classifier: Development Status :: 4 - Beta
Classifier: Intended Audience :: Developers
Classifier: License :: OSI Approved :: MIT License
Classifier: Programming Language :: Python :: 3
Classifier: Programming Language :: Python :: 3.11
Classifier: Programming Language :: Python :: 3.12
Classifier: Programming Language :: Python :: 3.13
Classifier: Programming Language :: Python :: 3 :: Only
Classifier: Topic :: Text Processing :: Markup
Classifier: Topic :: Utilities
Provides-Extra: all
Provides-Extra: all-formats
Provides-Extra: all-llm
Provides-Extra: anthropic
Provides-Extra: docs
Provides-Extra: epub
Provides-Extra: fast
Provides-Extra: google
Provides-Extra: html
Provides-Extra: latex
Provides-Extra: llm
Provides-Extra: local
Provides-Extra: mistral
Provides-Extra: openai
Provides-Extra: pdf
Provides-Extra: word
Requires-Dist: anthropic (>=0.7.0) ; extra == "anthropic" or extra == "all-llm" or extra == "all"
Requires-Dist: beautifulsoup4 (>=4.12.0)
Requires-Dist: browser-cookie3 (>=0.19.0)
Requires-Dist: click (>=8.1.0)
Requires-Dist: ebooklib (>=0.18.0) ; extra == "epub" or extra == "all-formats" or extra == "all"
Requires-Dist: google-generativeai (>=0.3.0) ; extra == "google" or extra == "all-llm" or extra == "all"
Requires-Dist: httpx[http2] (>=0.25.0)
Requires-Dist: jinja2 (>=3.1.0) ; extra == "latex" or extra == "html" or extra == "all-formats" or extra == "all"
Requires-Dist: litellm (>=1.30.5) ; extra == "llm" or extra == "all-llm" or extra == "all"
Requires-Dist: llama-cpp-python (>=0.2.0) ; extra == "local" or extra == "all-llm" or extra == "all"
Requires-Dist: lxml (>=4.9.0)
Requires-Dist: mistralai (>=0.0.7) ; extra == "mistral" or extra == "all-llm" or extra == "all"
Requires-Dist: openai (>=1.0.0) ; extra == "openai" or extra == "all-llm" or extra == "all"
Requires-Dist: pydantic (>=2.0.0)
Requires-Dist: python-dateutil (>=2.8.0)
Requires-Dist: python-docx (>=1.1.0) ; extra == "word" or extra == "all-formats" or extra == "all"
Requires-Dist: reportlab (>=4.0.0) ; extra == "pdf" or extra == "all-formats" or extra == "all"
Requires-Dist: rich (>=13.0.0)
Requires-Dist: tiktoken (>=0.5.0) ; extra == "llm" or extra == "all-llm" or extra == "all"
Requires-Dist: types-setuptools (>=80.8.0.20250521,<81.0.0.0)
Project-URL: Changelog, https://github.com/MarcusElwin/medium-converter/blob/main/CHANGELOG.md
Project-URL: Documentation, https://medium-converter.readthedocs.io
Project-URL: Homepage, https://github.com/MarcusElwin/medium-converter
Project-URL: Issues, https://github.com/MarcusElwin/medium-converter/issues
Project-URL: Repository, https://github.com/MarcusElwin/medium-converter
